lxstats/__init__.py
lxstats/fs.py
lxstats/files/__init__.py
lxstats/files/directory.py
lxstats/files/text.py
lxstats/files/types.py
lxstats/files/proc/__init__.py
lxstats/files/proc/process.py
lxstats/files/proc/system.py
lxstats/files/sys/__init__.py
lxstats/process/__init__.py
lxstats/process/collection.py
lxstats/process/filter.py
lxstats/process/formatter.py
lxstats/process/process.py
lxstats/process/formatters/__init__.py
lxstats/process/formatters/fmt_csv.py
lxstats/process/formatters/fmt_json.py
lxstats/process/formatters/fmt_table.py
lxstats/scripts/__init__.py
lxstats/scripts/procs.py
lxstats/tracing/__init__.py
lxstats/tracing/tracer.py
lxstats/tracing/types.py
lxstats-0.4.0.dist-info/LICENSE.txt
lxstats-0.4.0.dist-info/METADATA
lxstats-0.4.0.dist-info/WHEEL
lxstats-0.4.0.dist-info/entry_points.txt
lxstats-0.4.0.dist-info/top_level.txt
lxstats-0.4.0.dist-info/RECORD
