Metadata-Version: 2.1
Name: lxstats
Version: 0.4.0
Summary: Library to interact with files under /proc and /sys on Linux
Author-email: Alberto Donato <alberto.donato@gmail.com>
Maintainer-email: Alberto Donato <alberto.donato@gmail.com>
License: GNU LESSER GENERAL PUBLIC LICENSE
Project-URL: changelog, https://github.com/albertodonato/lxstats/blob/main/CHANGES.rst
Project-URL: homepage, https://github.com/albertodonato/lxstats
Project-URL: repository, https://github.com/albertodonato/lxstats
Keywords: admin,linux,monitoring,performance,proc,sys,system
Classifier: Development Status :: 4 - Beta
Classifier: Environment :: Console
Classifier: Intended Audience :: System Administrators
Classifier: License :: OSI Approved :: GNU Lesser General Public License v3 or later (LGPLv3+)
Classifier: Operating System :: POSIX :: Linux
Classifier: Programming Language :: Python :: 3
Classifier: Topic :: System :: Benchmark
Classifier: Topic :: System :: Monitoring
Classifier: Topic :: System :: Networking :: Monitoring
Classifier: Topic :: System :: Systems Administration
Classifier: Topic :: Utilities
Requires-Python: >=3.10
License-File: LICENSE.txt
Requires-Dist: prettytable
Requires-Dist: toolrack (>=2.0.1)
Provides-Extra: testing
Requires-Dist: pytest ; extra == 'testing'
Requires-Dist: pytest-mock ; extra == 'testing'
